LICENSE
MANIFEST.in
README.md
requirements.txt
setup.py
peeemtee/__init__.py
peeemtee/constants.py
peeemtee/pmt_resp_func.py
peeemtee/tools.py
peeemtee.egg-info/PKG-INFO
peeemtee.egg-info/SOURCES.txt
peeemtee.egg-info/dependency_links.txt
peeemtee.egg-info/entry_points.txt
peeemtee.egg-info/requires.txt
peeemtee.egg-info/top_level.txt
peeemtee/data/phdqe.txt