Metadata-Version: 1.1
Name: peeemtee
Version: 0.0.4
Summary: PeeEmTee
Home-page: https://github.com/JonasReubelt/PeeEmTee
Author: Jonas Reubelt
Author-email: jonas.reujon.reubelt@fau.de
License: UNKNOWN
Platform: any
Classifier: Development Status :: 3 - Alpha
Classifier: Intended Audience :: Developers
Classifier: Intended Audience :: Science/Research
Classifier: Programming Language :: Python
